README.md
pyproject.toml
setup.cfg
setup.py
rubCipherX/__init__.py
rubCipherX/client.py
rubCipherX.egg-info/PKG-INFO
rubCipherX.egg-info/SOURCES.txt
rubCipherX.egg-info/dependency_links.txt
rubCipherX.egg-info/requires.txt
rubCipherX.egg-info/top_level.txt
rubCipherX/crypto/__init__.py
rubCipherX/crypto/crypto.py
rubCipherX/gadgets/__init__.py
rubCipherX/gadgets/classino.py
rubCipherX/gadgets/exceptions.py
rubCipherX/gadgets/methods.py
rubCipherX/network/__init__.py
rubCipherX/network/connection.py
rubCipherX/network/proxies.py
rubCipherX/sessions/__init__.py
rubCipherX/sessions/sqliteSession.py
rubCipherX/sessions/stringSession.py
rubCipherX/structs/__init__.py
rubCipherX/structs/handlers.py
rubCipherX/structs/models.py
rubCipherX/structs/results.py
rubCipherX/structs/struct.py